tmin/__init__.py
tmin/core_dev.py
tmin/report_generator.py
tmin/tables/ANSI_radii.py
tmin/tables/__init__.py
tmin/tables/api_574_2009.py
tmin/tables/api_574_2025.py
tmin/tables/id_table.py
tmin/tables/od_table.py
tmin/tables/wsrf.py
tmin/tables/y_coeff.py
tmin-1.0.1.dist-info/licenses/LICENSE
tmin-1.0.1.dist-info/METADATA
tmin-1.0.1.dist-info/WHEEL
tmin-1.0.1.dist-info/entry_points.txt
tmin-1.0.1.dist-info/top_level.txt
tmin-1.0.1.dist-info/RECORD
