Metadata-Version: 2.4
Name: tmin
Version: 1.0.1
Summary: A comprehensive pipe thickness analysis tool for mechanical integrity engineering
Author-email: Andrew Trepagnier <andrew.trepagnier@icloud.com>
License: MIT
Project-URL: Homepage, https://github.com/AndrewTrepagnier/tmin
Project-URL: Repository, https://github.com/AndrewTrepagnier/tmin
Project-URL: Issues, https://github.com/AndrewTrepagnier/tmin/issues
Classifier: Development Status :: 4 - Beta
Classifier: Intended Audience :: Science/Research
Classifier: License :: OSI Approved :: MIT License
Classifier: Operating System :: OS Independent
Classifier: Programming Language :: Python :: 3
Classifier: Programming Language :: Python :: 3.8
Classifier: Programming Language :: Python :: 3.9
Classifier: Programming Language :: Python :: 3.10
Classifier: Programming Language :: Python :: 3.11
Classifier: Topic :: Scientific/Engineering
Classifier: Topic :: Scientific/Engineering :: Physics
Requires-Python: >=3.8
License-File: LICENSE
Requires-Dist: numpy>=1.23
Requires-Dist: matplotlib>=3.5
Requires-Dist: sympy>=1.11
Requires-Dist: toml>=0.10.0
Requires-Dist: jupyter>=1.0.0
Requires-Dist: notebook>=6.0.0
Provides-Extra: dev
Requires-Dist: pytest>=7.0; extra == "dev"
Requires-Dist: pytest-cov>=4.0; extra == "dev"
Requires-Dist: pytest-xdist>=3.0; extra == "dev"
Requires-Dist: black>=22.0; extra == "dev"
Requires-Dist: flake8>=5.0; extra == "dev"
Requires-Dist: mypy>=1.0; extra == "dev"
Dynamic: license-file
